m1_project_agne/__init__.py
m1_project_agne/krepsinis.py
m1_project_agne/main.py
m1_project_agne-0.1.1.dist-info/METADATA
m1_project_agne-0.1.1.dist-info/WHEEL
m1_project_agne-0.1.1.dist-info/RECORD
